{
 "cons_mix_s33": {
  "traj": [
   0.875,
   0.636,
   0.833,
   0.583,
   0.716
  ],
  "rounds": [
   {
    "pool_share": 0.5,
    "kept_cogen_share": 0.417,
    "risk_self": 0.944,
    "risk_cogen": 0.667,
    "matched_kept_pref": 0.5,
    "matched_kept_n": 40,
    "matched_score_pref": 0.486,
    "matched_score_n": 70
   },
   {
    "pool_share": 0.5,
    "kept_cogen_share": 0.208,
    "risk_self": 0.694,
    "risk_cogen": 0.639,
    "matched_kept_pref": 0.216,
    "matched_kept_n": 37,
    "matched_score_pref": 0.267,
    "matched_score_n": 60
   },
   {
    "pool_share": 0.5,
    "kept_cogen_share": 0.292,
    "risk_self": 0.75,
    "risk_cogen": 0.583,
    "matched_kept_pref": 0.158,
    "matched_kept_n": 38,
    "matched_score_pref": 0.194,
    "matched_score_n": 62
   },
   {
    "pool_share": 0.5,
    "kept_cogen_share": 0.167,
    "risk_self": 0.611,
    "risk_cogen": 0.611,
    "matched_kept_pref": 0.15,
    "matched_kept_n": 40,
    "matched_score_pref": 0.281,
    "matched_score_n": 64
   }
  ]
 },
 "cons_mix_s34": {
  "traj": [
   1.0,
   0.958,
   1.0,
   1.0,
   1.0
  ],
  "rounds": [
   {
    "pool_share": 0.5,
    "kept_cogen_share": 0.042,
    "risk_self": 1.0,
    "risk_cogen": 0.444,
    "matched_kept_pref": 0.0,
    "matched_kept_n": 30,
    "matched_score_pref": 0.0,
    "matched_score_n": 48
   },
   {
    "pool_share": 0.5,
    "kept_cogen_share": 0.042,
    "risk_self": 0.972,
    "risk_cogen": 0.667,
    "matched_kept_pref": 0.043,
    "matched_kept_n": 46,
    "matched_score_pref": 0.082,
    "matched_score_n": 73
   },
   {
    "pool_share": 0.5,
    "kept_cogen_share": 0.0,
    "risk_self": 1.0,
    "risk_cogen": 0.556,
    "matched_kept_pref": 0.0,
    "matched_kept_n": 40,
    "matched_score_pref": 0.017,
    "matched_score_n": 60
   },
   {
    "pool_share": 0.5,
    "kept_cogen_share": 0.0,
    "risk_self": 1.0,
    "risk_cogen": 0.694,
    "matched_kept_pref": 0.0,
    "matched_kept_n": 50,
    "matched_score_pref": 0.0,
    "matched_score_n": 75
   }
  ]
 },
 "h2h_base_rescue_s57": {
  "traj": [
   0.875,
   0.652,
   0.417,
   0.636,
   0.537
  ],
  "rounds": [
   {
    "pool_share": 0.5,
    "kept_cogen_share": 0.625,
    "risk_self": 0.972,
    "risk_cogen": 0.528,
    "matched_kept_pref": 0.7,
    "matched_kept_n": 30,
    "matched_score_pref": 0.074,
    "matched_score_n": 54
   },
   {
    "pool_share": 0.5,
    "kept_cogen_share": 0.417,
    "risk_self": 0.583,
    "risk_cogen": 0.667,
    "matched_kept_pref": 0.314,
    "matched_kept_n": 35,
    "matched_score_pref": 0.453,
    "matched_score_n": 53
   },
   {
    "pool_share": 0.5,
    "kept_cogen_share": 0.542,
    "risk_self": 0.667,
    "risk_cogen": 0.611,
    "matched_kept_pref": 0.541,
    "matched_kept_n": 37,
    "matched_score_pref": 0.516,
    "matched_score_n": 64
   },
   {
    "pool_share": 0.5,
    "kept_cogen_share": 0.625,
    "risk_self": 0.694,
    "risk_cogen": 0.722,
    "matched_kept_pref": 0.606,
    "matched_kept_n": 33,
    "matched_score_pref": 0.444,
    "matched_score_n": 63
   }
  ]
 },
 "h2h_base_rescue_s58": {
  "traj": [
   1.0,
   0.625,
   0.609,
   0.591,
   0.552
  ],
  "rounds": [
   {
    "pool_share": 0.5,
    "kept_cogen_share": 0.542,
    "risk_self": 1.0,
    "risk_cogen": 0.639,
    "matched_kept_pref": 0.553,
    "matched_kept_n": 38,
    "matched_score_pref": 0.0,
    "matched_score_n": 69
   },
   {
    "pool_share": 0.5,
    "kept_cogen_share": 0.417,
    "risk_self": 0.889,
    "risk_cogen": 0.639,
    "matched_kept_pref": 0.308,
    "matched_kept_n": 39,
    "matched_score_pref": 0.239,
    "matched_score_n": 71
   },
   {
    "pool_share": 0.5,
    "kept_cogen_share": 0.5,
    "risk_self": 0.667,
    "risk_cogen": 0.528,
    "matched_kept_pref": 0.316,
    "matched_kept_n": 38,
    "matched_score_pref": 0.322,
    "matched_score_n": 59
   },
   {
    "pool_share": 0.493,
    "kept_cogen_share": 0.458,
    "risk_self": 0.694,
    "risk_cogen": 0.571,
    "matched_kept_pref": 0.226,
    "matched_kept_n": 31,
    "matched_score_pref": 0.516,
    "matched_score_n": 62
   }
  ]
 },
 "h2h_cons_rescue_s55": {
  "traj": [
   0.865,
   0.682,
   0.5,
   0.542,
   0.537
  ],
  "rounds": [
   {
    "pool_share": 0.493,
    "kept_cogen_share": 0.5,
    "risk_self": 0.889,
    "risk_cogen": 0.629,
    "matched_kept_pref": 0.483,
    "matched_kept_n": 29,
    "matched_score_pref": 0.311,
    "matched_score_n": 61
   },
   {
    "pool_share": 0.5,
    "kept_cogen_share": 0.625,
    "risk_self": 0.778,
    "risk_cogen": 0.472,
    "matched_kept_pref": 0.676,
    "matched_kept_n": 37,
    "matched_score_pref": 0.365,
    "matched_score_n": 63
   },
   {
    "pool_share": 0.5,
    "kept_cogen_share": 0.542,
    "risk_self": 0.611,
    "risk_cogen": 0.528,
    "matched_kept_pref": 0.36,
    "matched_kept_n": 25,
    "matched_score_pref": 0.431,
    "matched_score_n": 51
   },
   {
    "pool_share": 0.5,
    "kept_cogen_share": 0.5,
    "risk_self": 0.583,
    "risk_cogen": 0.667,
    "matched_kept_pref": 0.487,
    "matched_kept_n": 39,
    "matched_score_pref": 0.635,
    "matched_score_n": 63
   }
  ]
 },
 "h2h_cons_rescue_s56": {
  "traj": [
   1.0,
   0.917,
   0.667,
   0.833,
   0.747
  ],
  "rounds": [
   {
    "pool_share": 0.5,
    "kept_cogen_share": 0.458,
    "risk_self": 1.0,
    "risk_cogen": 0.694,
    "matched_kept_pref": 0.405,
    "matched_kept_n": 42,
    "matched_score_pref": 0.027,
    "matched_score_n": 75
   },
   {
    "pool_share": 0.5,
    "kept_cogen_share": 0.458,
    "risk_self": 0.833,
    "risk_cogen": 0.639,
    "matched_kept_pref": 0.421,
    "matched_kept_n": 38,
    "matched_score_pref": 0.317,
    "matched_score_n": 63
   },
   {
    "pool_share": 0.5,
    "kept_cogen_share": 0.417,
    "risk_self": 0.722,
    "risk_cogen": 0.472,
    "matched_kept_pref": 0.37,
    "matched_kept_n": 27,
    "matched_score_pref": 0.458,
    "matched_score_n": 59
   },
   {
    "pool_share": 0.493,
    "kept_cogen_share": 0.25,
    "risk_self": 0.694,
    "risk_cogen": 0.686,
    "matched_kept_pref": 0.209,
    "matched_kept_n": 43,
    "matched_score_pref": 0.317,
    "matched_score_n": 60
   }
  ]
 },
 "h2h_invade_base_s51": {
  "traj": [
   0.33,
   0.708,
   0.875,
   0.917,
   0.74
  ],
  "rounds": [
   {
    "pool_share": 0.5,
    "kept_cogen_share": 0.583,
    "risk_self": 0.361,
    "risk_cogen": 1.0,
    "matched_kept_pref": 0.684,
    "matched_kept_n": 19,
    "matched_score_pref": 1.0,
    "matched_score_n": 39
   },
   {
    "pool_share": 0.5,
    "kept_cogen_share": 0.667,
    "risk_self": 0.583,
    "risk_cogen": 1.0,
    "matched_kept_pref": 0.636,
    "matched_kept_n": 33,
    "matched_score_pref": 0.628,
    "matched_score_n": 43
   },
   {
    "pool_share": 0.5,
    "kept_cogen_share": 0.458,
    "risk_self": 0.833,
    "risk_cogen": 1.0,
    "matched_kept_pref": 0.464,
    "matched_kept_n": 56,
    "matched_score_pref": 0.491,
    "matched_score_n": 57
   },
   {
    "pool_share": 0.5,
    "kept_cogen_share": 0.458,
    "risk_self": 0.806,
    "risk_cogen": 1.0,
    "matched_kept_pref": 0.609,
    "matched_kept_n": 46,
    "matched_score_pref": 0.333,
    "matched_score_n": 33
   }
  ]
 },
 "h2h_invade_base_s52": {
  "traj": [
   0.286,
   0.652,
   0.958,
   0.958,
   0.938
  ],
  "rounds": [
   {
    "pool_share": 0.5,
    "kept_cogen_share": 0.708,
    "risk_self": 0.306,
    "risk_cogen": 1.0,
    "matched_kept_pref": 0.765,
    "matched_kept_n": 17,
    "matched_score_pref": 1.0,
    "matched_score_n": 33
   },
   {
    "pool_share": 0.5,
    "kept_cogen_share": 0.75,
    "risk_self": 0.667,
    "risk_cogen": 1.0,
    "matched_kept_pref": 0.85,
    "matched_kept_n": 40,
    "matched_score_pref": 0.6,
    "matched_score_n": 50
   },
   {
    "pool_share": 0.5,
    "kept_cogen_share": 0.417,
    "risk_self": 0.833,
    "risk_cogen": 1.0,
    "matched_kept_pref": 0.451,
    "matched_kept_n": 51,
    "matched_score_pref": 0.516,
    "matched_score_n": 64
   },
   {
    "pool_share": 0.5,
    "kept_cogen_share": 0.583,
    "risk_self": 0.889,
    "risk_cogen": 1.0,
    "matched_kept_pref": 0.577,
    "matched_kept_n": 52,
    "matched_score_pref": 0.271,
    "matched_score_n": 48
   }
  ]
 },
 "h2h_invade_self_s53": {
  "traj": [
   0.3,
   0.696,
   0.958,
   1.0,
   1.0
  ],
  "rounds": [
   {
    "pool_share": 0.5,
    "kept_cogen_share": 0.708,
    "risk_self": 0.278,
    "risk_cogen": 1.0,
    "matched_kept_pref": 0.789,
    "matched_kept_n": 19,
    "matched_score_pref": 0.967,
    "matched_score_n": 30
   },
   {
    "pool_share": 0.5,
    "kept_cogen_share": 0.625,
    "risk_self": 0.75,
    "risk_cogen": 1.0,
    "matched_kept_pref": 0.56,
    "matched_kept_n": 50,
    "matched_score_pref": 0.812,
    "matched_score_n": 69
   },
   {
    "pool_share": 0.5,
    "kept_cogen_share": 0.375,
    "risk_self": 0.972,
    "risk_cogen": 1.0,
    "matched_kept_pref": 0.371,
    "matched_kept_n": 70,
    "matched_score_pref": 0.605,
    "matched_score_n": 81
   },
   {
    "pool_share": 0.5,
    "kept_cogen_share": 0.583,
    "risk_self": 1.0,
    "risk_cogen": 1.0,
    "matched_kept_pref": 0.594,
    "matched_kept_n": 64,
    "matched_score_pref": 0.203,
    "matched_score_n": 59
   }
  ]
 },
 "h2h_invade_self_s54": {
  "traj": [
   0.207,
   0.708,
   0.833,
   1.0,
   1.0
  ],
  "rounds": [
   {
    "pool_share": 0.5,
    "kept_cogen_share": 0.5,
    "risk_self": 0.361,
    "risk_cogen": 1.0,
    "matched_kept_pref": 0.36,
    "matched_kept_n": 25,
    "matched_score_pref": 0.974,
    "matched_score_n": 39
   },
   {
    "pool_share": 0.5,
    "kept_cogen_share": 0.542,
    "risk_self": 0.583,
    "risk_cogen": 1.0,
    "matched_kept_pref": 0.351,
    "matched_kept_n": 37,
    "matched_score_pref": 0.831,
    "matched_score_n": 59
   },
   {
    "pool_share": 0.5,
    "kept_cogen_share": 0.625,
    "risk_self": 0.889,
    "risk_cogen": 1.0,
    "matched_kept_pref": 0.621,
    "matched_kept_n": 58,
    "matched_score_pref": 0.661,
    "matched_score_n": 56
   },
   {
    "pool_share": 0.5,
    "kept_cogen_share": 0.583,
    "risk_self": 1.0,
    "risk_cogen": 1.0,
    "matched_kept_pref": 0.6,
    "matched_kept_n": 60,
    "matched_score_pref": 0.07,
    "matched_score_n": 43
   }
  ]
 },
 "invade_base_s35": {
  "traj": [
   0.307,
   1.0,
   1.0,
   1.0,
   0.989
  ],
  "rounds": [
   {
    "pool_share": 0.5,
    "kept_cogen_share": 0.958,
    "risk_self": 0.25,
    "risk_cogen": 1.0,
    "matched_kept_pref": 1.0,
    "matched_kept_n": 18,
    "matched_score_pref": 1.0,
    "matched_score_n": 27
   },
   {
    "pool_share": 0.5,
    "kept_cogen_share": 0.417,
    "risk_self": 1.0,
    "risk_cogen": 1.0,
    "matched_kept_pref": 0.393,
    "matched_kept_n": 56,
    "matched_score_pref": 0.059,
    "matched_score_n": 51
   },
   {
    "pool_share": 0.5,
    "kept_cogen_share": 0.375,
    "risk_self": 1.0,
    "risk_cogen": 1.0,
    "matched_kept_pref": 0.333,
    "matched_kept_n": 54,
    "matched_score_pref": 0.059,
    "matched_score_n": 51
   },
   {
    "pool_share": 0.5,
    "kept_cogen_share": 0.417,
    "risk_self": 1.0,
    "risk_cogen": 1.0,
    "matched_kept_pref": 0.385,
    "matched_kept_n": 52,
    "matched_score_pref": 0.077,
    "matched_score_n": 39
   }
  ]
 },
 "invade_base_s36": {
  "traj": [
   0.312,
   1.0,
   1.0,
   0.958,
   1.0
  ],
  "rounds": [
   {
    "pool_share": 0.5,
    "kept_cogen_share": 1.0,
    "risk_self": 0.389,
    "risk_cogen": 1.0,
    "matched_kept_pref": 1.0,
    "matched_kept_n": 28,
    "matched_score_pref": 1.0,
    "matched_score_n": 42
   },
   {
    "pool_share": 0.5,
    "kept_cogen_share": 0.375,
    "risk_self": 1.0,
    "risk_cogen": 1.0,
    "matched_kept_pref": 0.355,
    "matched_kept_n": 62,
    "matched_score_pref": 0.27,
    "matched_score_n": 74
   },
   {
    "pool_share": 0.5,
    "kept_cogen_share": 0.417,
    "risk_self": 1.0,
    "risk_cogen": 1.0,
    "matched_kept_pref": 0.4,
    "matched_kept_n": 60,
    "matched_score_pref": 0.167,
    "matched_score_n": 54
   },
   {
    "pool_share": 0.5,
    "kept_cogen_share": 0.375,
    "risk_self": 1.0,
    "risk_cogen": 1.0,
    "matched_kept_pref": 0.355,
    "matched_kept_n": 62,
    "matched_score_pref": 0.19,
    "matched_score_n": 58
   }
  ]
 },
 "invade_self_s37": {
  "traj": [
   0.363,
   0.917,
   1.0,
   1.0,
   1.0
  ],
  "rounds": [
   {
    "pool_share": 0.5,
    "kept_cogen_share": 0.958,
    "risk_self": 0.306,
    "risk_cogen": 1.0,
    "matched_kept_pref": 1.0,
    "matched_kept_n": 22,
    "matched_score_pref": 0.97,
    "matched_score_n": 33
   },
   {
    "pool_share": 0.5,
    "kept_cogen_share": 0.417,
    "risk_self": 0.917,
    "risk_cogen": 1.0,
    "matched_kept_pref": 0.37,
    "matched_kept_n": 54,
    "matched_score_pref": 0.219,
    "matched_score_n": 32
   },
   {
    "pool_share": 0.5,
    "kept_cogen_share": 0.583,
    "risk_self": 1.0,
    "risk_cogen": 1.0,
    "matched_kept_pref": 0.6,
    "matched_kept_n": 60,
    "matched_score_pref": 0.558,
    "matched_score_n": 52
   },
   {
    "pool_share": 0.5,
    "kept_cogen_share": 0.5,
    "risk_self": 1.0,
    "risk_cogen": 1.0,
    "matched_kept_pref": 0.5,
    "matched_kept_n": 56,
    "matched_score_pref": 0.452,
    "matched_score_n": 73
   }
  ]
 },
 "invade_self_s38": {
  "traj": [
   0.244,
   1.0,
   1.0,
   1.0,
   1.0
  ],
  "rounds": [
   {
    "pool_share": 0.5,
    "kept_cogen_share": 1.0,
    "risk_self": 0.389,
    "risk_cogen": 1.0,
    "matched_kept_pref": 1.0,
    "matched_kept_n": 28,
    "matched_score_pref": 0.976,
    "matched_score_n": 42
   },
   {
    "pool_share": 0.5,
    "kept_cogen_share": 0.292,
    "risk_self": 1.0,
    "risk_cogen": 1.0,
    "matched_kept_pref": 0.241,
    "matched_kept_n": 58,
    "matched_score_pref": 0.414,
    "matched_score_n": 70
   },
   {
    "pool_share": 0.5,
    "kept_cogen_share": 0.292,
    "risk_self": 1.0,
    "risk_cogen": 1.0,
    "matched_kept_pref": 0.241,
    "matched_kept_n": 58,
    "matched_score_pref": 0.188,
    "matched_score_n": 64
   },
   {
    "pool_share": 0.5,
    "kept_cogen_share": 0.458,
    "risk_self": 1.0,
    "risk_cogen": 1.0,
    "matched_kept_pref": 0.452,
    "matched_kept_n": 62,
    "matched_score_pref": 0.302,
    "matched_score_n": 86
   }
  ]
 },
 "oracle_mix_s31": {
  "traj": [
   0.927,
   0.652,
   0.565,
   0.375,
   0.344
  ],
  "rounds": [
   {
    "pool_share": 0.5,
    "kept_cogen_share": 0.75,
    "risk_self": 0.917,
    "risk_cogen": 0.583,
    "matched_kept_pref": 0.6,
    "matched_kept_n": 15,
    "matched_score_pref": null,
    "matched_score_n": 0
   },
   {
    "pool_share": 0.5,
    "kept_cogen_share": 0.542,
    "risk_self": 0.528,
    "risk_cogen": 0.556,
    "matched_kept_pref": 0.63,
    "matched_kept_n": 27,
    "matched_score_pref": null,
    "matched_score_n": 0
   },
   {
    "pool_share": 0.5,
    "kept_cogen_share": 0.625,
    "risk_self": 0.611,
    "risk_cogen": 0.528,
    "matched_kept_pref": 0.667,
    "matched_kept_n": 18,
    "matched_score_pref": null,
    "matched_score_n": 0
   },
   {
    "pool_share": 0.5,
    "kept_cogen_share": 0.417,
    "risk_self": 0.333,
    "risk_cogen": 0.639,
    "matched_kept_pref": 0.739,
    "matched_kept_n": 23,
    "matched_score_pref": null,
    "matched_score_n": 0
   }
  ]
 },
 "oracle_mix_s32": {
  "traj": [
   1.0,
   0.75,
   0.458,
   0.208,
   0.484
  ],
  "rounds": [
   {
    "pool_share": 0.5,
    "kept_cogen_share": 0.708,
    "risk_self": 1.0,
    "risk_cogen": 0.694,
    "matched_kept_pref": 0.556,
    "matched_kept_n": 36,
    "matched_score_pref": null,
    "matched_score_n": 0
   },
   {
    "pool_share": 0.5,
    "kept_cogen_share": 0.625,
    "risk_self": 0.75,
    "risk_cogen": 0.611,
    "matched_kept_pref": 0.667,
    "matched_kept_n": 21,
    "matched_score_pref": null,
    "matched_score_n": 0
   },
   {
    "pool_share": 0.5,
    "kept_cogen_share": 0.458,
    "risk_self": 0.556,
    "risk_cogen": 0.667,
    "matched_kept_pref": 0.65,
    "matched_kept_n": 20,
    "matched_score_pref": null,
    "matched_score_n": 0
   },
   {
    "pool_share": 0.5,
    "kept_cogen_share": 0.5,
    "risk_self": 0.667,
    "risk_cogen": 0.583,
    "matched_kept_pref": 0.423,
    "matched_kept_n": 26,
    "matched_score_pref": null,
    "matched_score_n": 0
   }
  ]
 }
}